walletboy.py
walletboy-1.0.2.dist-info/LICENSE
walletboy-1.0.2.dist-info/WHEEL
walletboy-1.0.2.dist-info/METADATA
walletboy-1.0.2.dist-info/RECORD
