Metadata-Version: 2.1
Name: walletboy
Version: 1.0.2
Summary: Crypto wallet application
Author-email: Marques Traylor <traylorboy@proton.me>
Classifier: License :: OSI Approved :: MIT License
Requires-Dist: coinbasepro
Requires-Dist: python-dotenv
Project-URL: Home, https://github.com/TraylorBoy/WalletBoy
